<annotation>
	<folder>JPEGImages</folder>
	<filename>Sooty_Albatross_0013_796402.jpg</filename>
	<path>C:\Users\Lenovo\Desktop\menue\chengying-1-bird-1\JPEGImages\Sooty_Albatross_0013_796402.jpg</path>
	<source>
		<database>Unknown</database>
	</source>
	<size>
		<width>320</width>
		<height>240</height>
		<depth>3</depth>
	</size>
	<segmented>0</segmented>
	<object>
		<name>bird</name>
		<pose>Unspecified</pose>
		<truncated>0</truncated>
		<difficult>0</difficult>
		<bndbox>
			<xmin>81</xmin>
			<ymin>41</ymin>
			<xmax>245</xmax>
			<ymax>194</ymax>
		</bndbox>
	</object>
</annotation>
