<annotation>
	<folder>JPEGImages</folder>
	<filename>Western_Wood_Pewee_0024_98229.jpg</filename>
	<path>C:\Users\Lenovo\Desktop\menue\chengying-1-bird-1\JPEGImages\Western_Wood_Pewee_0024_98229.jpg</path>
	<source>
		<database>Unknown</database>
	</source>
	<size>
		<width>400</width>
		<height>500</height>
		<depth>3</depth>
	</size>
	<segmented>0</segmented>
	<object>
		<name>bird</name>
		<pose>Unspecified</pose>
		<truncated>0</truncated>
		<difficult>0</difficult>
		<bndbox>
			<xmin>152</xmin>
			<ymin>130</ymin>
			<xmax>331</xmax>
			<ymax>356</ymax>
		</bndbox>
	</object>
</annotation>
